python_download_manager/__init__.py
python_download_manager/__main__.py
python_download_manager/_cli.py
python_download_manager/_consts.py
python_download_manager/_decorators.py
python_download_manager/_download_manager.py
python_download_manager/_structures.py
python_download_manager/_typehint.py
python_download_manager/_utility.py
python_download_manager/callbacks.py
python_download_manager/cli.py
python_download_manager/decorators.py
python_download_manager/download_manager.py
python_download_manager/process_manager.py
python_download_manager/utility.py
python_download_manager/_callbacks/__init__.py
python_download_manager/_callbacks/_core.py
python_download_manager/_database/__init__.py
python_download_manager/_database/_database_manager.py
python_download_manager/_database/_model.py
python_download_manager/_database/_viewmodel.py
python_download_manager/_progress/__init__.py
python_download_manager/_progress/_adapter.py
python_download_manager/_progress/_progress_manager.py
python_download_manager/_serialization/__init__.py
python_download_manager/_serialization/_coder.py
python_download_manager/_serialization/_core.py
python_download_manager/_serialization/_decorator.py
python_download_manager/_session_manager/__init__.py
python_download_manager/_session_manager/_core.py
python_download_manager/_storage/__init__.py
python_download_manager/_storage/_filewriter.py
python_download_manager/_storage/_storage_manager.py
python_download_manager/_task_scheduler/__init__.py
python_download_manager/_task_scheduler/_done_callbacks.py
python_download_manager/_task_scheduler/_scheduler.py
python_download_manager/_task_scheduler/_task_downloader.py
python_download_manager/_task_scheduler/_task_executor.py
python_download_manager/_unpack/__init__.py
python_download_manager/_unpack/_adapter.py
python_download_manager/_unpack/_core.py
python_download_manager/callbacks/__init__.py
python_download_manager/callbacks/_core.py
python_download_manager/database/__init__.py
python_download_manager-0.7.8.dist-info/LICENCE
python_download_manager-0.7.8.dist-info/METADATA
python_download_manager-0.7.8.dist-info/WHEEL
python_download_manager-0.7.8.dist-info/top_level.txt
python_download_manager-0.7.8.dist-info/RECORD
